odoo/addons/pos_sale_pos_event_sale/README.rst
odoo/addons/pos_sale_pos_event_sale/__init__.py
odoo/addons/pos_sale_pos_event_sale/__manifest__.py
odoo/addons/pos_sale_pos_event_sale/i18n/es.po
odoo/addons/pos_sale_pos_event_sale/i18n/it.po
odoo/addons/pos_sale_pos_event_sale/i18n/pos_sale_pos_event_sale.pot
odoo/addons/pos_sale_pos_event_sale/models/__init__.py
odoo/addons/pos_sale_pos_event_sale/models/pos_order_line.py
odoo/addons/pos_sale_pos_event_sale/models/sale_order_line.py
odoo/addons/pos_sale_pos_event_sale/readme/CONTRIBUTORS.rst
odoo/addons/pos_sale_pos_event_sale/readme/DESCRIPTION.rst
odoo/addons/pos_sale_pos_event_sale/static/description/icon.png
odoo/addons/pos_sale_pos_event_sale/static/description/index.html
odoo/addons/pos_sale_pos_event_sale/static/src/js/SaleOrderManagementScreen.js
odoo/addons/pos_sale_pos_event_sale/static/src/js/models.js
odoo/addons/pos_sale_pos_event_sale/static/tests/tours/PosEventSaleImport.tour.js
odoo/addons/pos_sale_pos_event_sale/static/tests/tours/helpers/ProductScreenTourMethods.js
odoo/addons/pos_sale_pos_event_sale/static/tests/tours/helpers/SaleOrderScreenTourMethods.js
odoo/addons/pos_sale_pos_event_sale/tests/__init__.py
odoo/addons/pos_sale_pos_event_sale/tests/test_frontend.py
odoo_addon_pos_sale_pos_event_sale-15.0.1.0.1.dist-info/METADATA
odoo_addon_pos_sale_pos_event_sale-15.0.1.0.1.dist-info/WHEEL
odoo_addon_pos_sale_pos_event_sale-15.0.1.0.1.dist-info/top_level.txt
odoo_addon_pos_sale_pos_event_sale-15.0.1.0.1.dist-info/RECORD
